Workbook

Sheet Summary
A1: Debtor Name | B1: Zomato
A2: Recon Period | B2: Dec 01, 2024 - Dec 07, 2024
B3: No. of orders | C3: POS Amount
A4: POS Sale as per Business Date (S1+S2) | B4: =COUNTA('Zomato POS vs 3PO'!A2:A1048576) | C4: =SUM('Zomato POS vs 3PO'!E2:E1048576)
A5: POS Sale as per Transaction Date (S1) | B5: =COUNTA('Zomato POS vs 3PO'!A2:A1048576) | C5: =SUM('Zomato POS vs 3PO'!E2:E1048576)
A6: Difference in POS Sale that falls in subsequent time period (S2) | B6: =B4-B5 | C6: =C4-C5
A8: POS Sale as per Business Date (S1+S2) | B8: As per POS data (POS vs 3PO) | G8: As per 3PO Data (3PO vs POS)
A9: Parameters | B9: No. of orders | C9: POS Amount/Calculated | D9: 3PO Amount/Actual | E9: Diff. in Amount | F9: Amount Receivable | G9: No. of orders | H9: 3PO Amount/Actual | I9: POS Amount/Calculated | J9: Diff. in Amount | K9: Amount Receivable
A10: DELIVERED (As per transaction date) | B10: =COUNTA('Zomato POS vs 3PO'!A2:A1048576) | C10: =SUM('Zomato POS vs 3PO'!E2:E1048576) | D10: =SUM('Zomato POS vs 3PO'!F2:F1048576) | E10: =C10-D10 | F10: =SUM('Zomato POS vs 3PO'!Z2:Z1048576) | G10: =COUNTA('Zomato 3PO vs POS'!A2:A1048576) | H10: =SUM('Zomato 3PO vs POS'!E2:E1048576) | I10: =SUM('Zomato 3PO vs POS'!F2:F1048576) | J10: =H10-I10 | K10: =SUM('Zomato 3PO vs POS'!Z2:Z1048576)
A11: SALE | G11: =COUNTIFS('Zomato 3PO vs POS'!A2:A1048576,"<>",'Zomato 3PO vs POS'!AY2:AY1048576,"sale") | H11: =SUMIFS('Zomato 3PO vs POS'!E2:E1048576,'Zomato 3PO vs POS'!E2:E1048576,"<>",'Zomato 3PO vs POS'!AY2:AY1048576,"sale") | I11: =SUMIFS('Zomato 3PO vs POS'!F2:F1048576,'Zomato 3PO vs POS'!F2:F1048576,"<>",'Zomato 3PO vs POS'!AY2:AY1048576,"sale") | J11: =H11-I11 | K11: =SUMIFS('Zomato 3PO vs POS'!Z2:Z1048576,'Zomato 3PO vs POS'!Z2:Z1048576,"<>",'Zomato 3PO vs POS'!AY2:AY1048576,"sale")
A12: ADDITION | G12: =COUNTIFS('Zomato 3PO vs POS'!A2:A1048576,"<>",'Zomato 3PO vs POS'!AY2:AY1048576,"addition") | H12: =SUMIFS('Zomato 3PO vs POS'!E2:E1048576,'Zomato 3PO vs POS'!E2:E1048576,"<>",'Zomato 3PO vs POS'!AY2:AY1048576,"addition") | I12: =SUMIFS('Zomato 3PO vs POS'!F2:F1048576,'Zomato 3PO vs POS'!F2:F1048576,"<>",'Zomato 3PO vs POS'!AY2:AY1048576,"addition") | J12: =H12-I12 | K12: =SUMIFS('Zomato 3PO vs POS'!Z2:Z1048576,'Zomato 3PO vs POS'!Z2:Z1048576,"<>",'Zomato 3PO vs POS'!AY2:AY1048576,"addition")
A13: REFUND | G13: =COUNTIFS('Zomato 3PO vs POS Refund'!A2:A1048576,"<>",'Zomato 3PO vs POS Refund'!AY2:AY1048576,"refund") | H13: =SUMIFS('Zomato 3PO vs POS Refund'!E2:E1048576,'Zomato 3PO vs POS Refund'!E2:E1048576,"<>",'Zomato 3PO vs POS Refund'!AY2:AY1048576,"refund") | I13: =SUMIFS('Zomato 3PO vs POS Refund'!F2:F1048576,'Zomato 3PO vs POS Refund'!F2:F1048576,"<>",'Zomato 3PO vs POS Refund'!AY2:AY1048576,"refund") | J13: =H13-I13 | K13: =SUMIFS('Zomato 3PO vs POS Refund'!Z2:Z1048576,'Zomato 3PO vs POS Refund'!Z2:Z1048576,"<>",'Zomato 3PO vs POS Refund'!AY2:AY1048576,"refund")
A15: Reconciled Orders | B15: =COUNTIF('Zomato POS vs 3PO'!AC2:AC1048576,"RECONCILED") | C15: =SUMIFS('Zomato POS vs 3PO'!E2:E1048576,'Zomato POS vs 3PO'!E2:E1048576,"<>",'Zomato POS vs 3PO'!AC2:AC1048576,"RECONCILED") | D15: =SUMIFS('Zomato POS vs 3PO'!F2:F1048576,'Zomato POS vs 3PO'!F2:F1048576,"<>",'Zomato POS vs 3PO'!AC2:AC1048576,"RECONCILED") | E15: =C15-D15 | F15: =SUMIFS('Zomato POS vs 3PO'!Z2:Z1048576,'Zomato POS vs 3PO'!Z2:Z1048576,"<>",'Zomato POS vs 3PO'!AC2:AC1048576,"RECONCILED") | G15: =COUNTIF('Zomato 3PO vs POS'!AU2:AU1048576,"RECONCILED") | H15: =SUMIFS('Zomato 3PO vs POS'!E2:E1048576,'Zomato 3PO vs POS'!E2:E1048576,"<>",'Zomato 3PO vs POS'!AU2:AU1048576,"RECONCILED") | I15: =SUMIFS('Zomato 3PO vs POS'!F2:F1048576,'Zomato 3PO vs POS'!F2:F1048576,"<>",'Zomato 3PO vs POS'!AU2:AU1048576,"RECONCILED") | J15: =H15-I15 | K15: =SUMIFS('Zomato 3PO vs POS'!Z2:Z1048576,'Zomato 3PO vs POS'!Z2:Z1048576,"<>",'Zomato 3PO vs POS'!AU2:AU1048576,"RECONCILED")
A16: Cancelled by Merchant and found in POS | B16: 0 | C16: 0 | D16: 0 | E16: 0 | F16: 0 | G16: 0 | H16: 0 | I16: 0 | J16: 0 | K16: 0
A17: Cancelled by Merchant and not found in POS | B17: 0 | C17: 0 | D17: 0 | E17: 0 | F17: 0 | G17: 0 | H17: 0 | I17: 0 | J17: 0 | K17: 0
A18: Unreconciled Orders | B18: =COUNTIF('Zomato POS vs 3PO'!AC2:AC1048576,"UNRECONCILED") | C18: =SUMIFS('Zomato POS vs 3PO'!E2:E1048576,'Zomato POS vs 3PO'!E2:E1048576,"<>",'Zomato POS vs 3PO'!AC2:AC1048576,"UNRECONCILED") | D18: =SUMIFS('Zomato POS vs 3PO'!F2:F1048576,'Zomato POS vs 3PO'!F2:F1048576,"<>",'Zomato POS vs 3PO'!AC2:AC1048576,"UNRECONCILED") | E18: =C18-D18 | F18: =SUMIFS('Zomato POS vs 3PO'!Z2:Z1048576,'Zomato POS vs 3PO'!Z2:Z1048576,"<>",'Zomato POS vs 3PO'!AC2:AC1048576,"UNRECONCILED") | G18: =COUNTIF('Zomato 3PO vs POS'!AU2:AU1048576,"UNRECONCILED") | H18: =SUMIFS('Zomato 3PO vs POS'!E2:E1048576,'Zomato 3PO vs POS'!E2:E1048576,"<>",'Zomato 3PO vs POS'!AU2:AU1048576,"UNRECONCILED") | I18: =SUMIFS('Zomato 3PO vs POS'!F2:F1048576,'Zomato 3PO vs POS'!F2:F1048576,"<>",'Zomato 3PO vs POS'!AU2:AU1048576,"UNRECONCILED") | J18: =H18-I18 | K18: =SUMIFS('Zomato 3PO vs POS'!Z2:Z1048576,'Zomato 3PO vs POS'!Z2:Z1048576,"<>",'Zomato 3PO vs POS'!AU2:AU1048576,"UNRECONCILED")
A19: Order Not found in 3PO/POS | B19: =COUNTIFS('Zomato POS vs 3PO'!AC2:AC1048576,"UNRECONCILED",'Zomato POS vs 3PO'!B2:B1048576,"") | C19: =SUMIFS('Zomato POS vs 3PO'!E2:E1048576,'Zomato POS vs 3PO'!E2:E1048576,"<>",'Zomato POS vs 3PO'!AC2:AC1048576,"UNRECONCILED",'Zomato POS vs 3PO'!B2:B1048576,"") | D19: =SUMIFS('Zomato POS vs 3PO'!F2:F1048576,'Zomato POS vs 3PO'!F2:F1048576,"<>",'Zomato POS vs 3PO'!AC2:AC1048576,"UNRECONCILED",'Zomato POS vs 3PO'!B2:B1048576,"") | E19: =C19-D19 | F19: =SUMIFS('Zomato POS vs 3PO'!Z2:Z1048576,'Zomato POS vs 3PO'!Z2:Z1048576,"<>",'Zomato POS vs 3PO'!AC2:AC1048576,"UNRECONCILED",'Zomato POS vs 3PO'!B2:B1048576,"") | G19: =COUNTIFS('Zomato 3PO vs POS'!AU2:AU1048576,"UNRECONCILED",'Zomato 3PO vs POS'!B2:B1048576,"") | H19: =SUMIFS('Zomato 3PO vs POS'!E2:E1048576,'Zomato 3PO vs POS'!E2:E1048576,"<>",'Zomato 3PO vs POS'!AU2:AU1048576,"UNRECONCILED",'Zomato 3PO vs POS'!B2:B1048576,"") | I19: =SUMIFS('Zomato 3PO vs POS'!F2:F1048576,'Zomato 3PO vs POS'!F2:F1048576,"<>",'Zomato 3PO vs POS'!AU2:AU1048576,"UNRECONCILED",'Zomato 3PO vs POS'!B2:B1048576,"") | J19: =H19-I19 | K19: =SUMIFS('Zomato 3PO vs POS'!Z2:Z1048576,'Zomato 3PO vs POS'!Z2:Z1048576,"<>",'Zomato 3PO vs POS'!AU2:AU1048576,"UNRECONCILED",'Zomato 3PO vs POS'!B2:B1048576,"")
A20: Net Amount mismatch | B20: =COUNTIFS('Zomato POS vs 3PO'!AC2:AC1048576,"UNRECONCILED",'Zomato POS vs 3PO'!AF2:AF1048576,"NET_AMOUNT_ZOMATO_POS_MISMATCH") | C20: =SUMIFS('Zomato POS vs 3PO'!E2:E1048576,'Zomato POS vs 3PO'!E2:E1048576,"<>",'Zomato POS vs 3PO'!AC2:AC1048576,"UNRECONCILED",'Zomato POS vs 3PO'!AF2:AF1048576,"NET_AMOUNT_ZOMATO_POS_MISMATCH") | D20: =SUMIFS('Zomato POS vs 3PO'!F2:F1048576,'Zomato POS vs 3PO'!F2:F1048576,"<>",'Zomato POS vs 3PO'!AC2:AC1048576,"UNRECONCILED",'Zomato POS vs 3PO'!AF2:AF1048576,"NET_AMOUNT_ZOMATO_POS_MISMATCH") | E20: =C20-D20 | F20: =SUMIFS('Zomato POS vs 3PO'!Z2:Z1048576,'Zomato POS vs 3PO'!Z2:Z1048576,"<>",'Zomato POS vs 3PO'!AC2:AC1048576,"UNRECONCILED",'Zomato POS vs 3PO'!AF2:AF1048576,"NET_AMOUNT_ZOMATO_POS_MISMATCH") | G20: =COUNTIFS('Zomato 3PO vs POS'!AU2:AU1048576,"UNRECONCILED",'Zomato 3PO vs POS'!AX2:AX1048576,"NET_AMOUNT_ZOMATO_POS_MISMATCH") | H20: =SUMIFS('Zomato 3PO vs POS'!E2:E1048576,'Zomato 3PO vs POS'!E2:E1048576,"<>",'Zomato 3PO vs POS'!AU2:AU1048576,"UNRECONCILED",'Zomato 3PO vs POS'!AX2:AX1048576,"NET_AMOUNT_ZOMATO_POS_MISMATCH") | I20: =SUMIFS('Zomato 3PO vs POS'!F2:F1048576,'Zomato 3PO vs POS'!F2:F1048576,"<>",'Zomato 3PO vs POS'!AU2:AU1048576,"UNRECONCILED",'Zomato 3PO vs POS'!AX2:AX1048576,"NET_AMOUNT_ZOMATO_POS_MISMATCH") | J20: =H20-I20 | K20: =SUMIFS('Zomato 3PO vs POS'!Z2:Z1048576,'Zomato 3PO vs POS'!Z2:Z1048576,"<>",'Zomato 3PO vs POS'!AU2:AU1048576,"UNRECONCILED",'Zomato 3PO vs POS'!AX2:AX1048576,"NET_AMOUNT_ZOMATO_POS_MISMATCH")
A21: Tax Paid by Customer mismatch | B21: =COUNTIFS('Zomato POS vs 3PO'!AC2:AC1048576,"UNRECONCILED",'Zomato POS vs 3PO'!AF2:AF1048576,"TAX_PAID_BY_CUSTOMER_ZOMATO_POS_MISMATCH") | C21: =SUMIFS('Zomato POS vs 3PO'!E2:E1048576,'Zomato POS vs 3PO'!E2:E1048576,"<>",'Zomato POS vs 3PO'!AC2:AC1048576,"UNRECONCILED",'Zomato POS vs 3PO'!AF2:AF1048576,"TAX_PAID_BY_CUSTOMER_ZOMATO_POS_MISMATCH") | D21: =SUMIFS('Zomato POS vs 3PO'!F2:F1048576,'Zomato POS vs 3PO'!F2:F1048576,"<>",'Zomato POS vs 3PO'!AC2:AC1048576,"UNRECONCILED",'Zomato POS vs 3PO'!AF2:AF1048576,"TAX_PAID_BY_CUSTOMER_ZOMATO_POS_MISMATCH") | E21: =C21-D21 | F21: =SUMIFS('Zomato POS vs 3PO'!Z2:Z1048576,'Zomato POS vs 3PO'!Z2:Z1048576,"<>",'Zomato POS vs 3PO'!AC2:AC1048576,"UNRECONCILED",'Zomato POS vs 3PO'!AF2:AF1048576,"TAX_PAID_BY_CUSTOMER_ZOMATO_POS_MISMATCH") | G21: =COUNTIFS('Zomato 3PO vs POS'!AU2:AU1048576,"UNRECONCILED",'Zomato 3PO vs POS'!AX2:AX1048576,"TAX_PAID_BY_CUSTOMER_ZOMATO_POS_MISMATCH") | H21: =SUMIFS('Zomato 3PO vs POS'!E2:E1048576,'Zomato 3PO vs POS'!E2:E1048576,"<>",'Zomato 3PO vs POS'!AU2:AU1048576,"UNRECONCILED",'Zomato 3PO vs POS'!AX2:AX1048576,"TAX_PAID_BY_CUSTOMER_ZOMATO_POS_MISMATCH") | I21: =SUMIFS('Zomato 3PO vs POS'!F2:F1048576,'Zomato 3PO vs POS'!F2:F1048576,"<>",'Zomato 3PO vs POS'!AU2:AU1048576,"UNRECONCILED",'Zomato 3PO vs POS'!AX2:AX1048576,"TAX_PAID_BY_CUSTOMER_ZOMATO_POS_MISMATCH") | J21: =H21-I21 | K21: =SUMIFS('Zomato 3PO vs POS'!Z2:Z1048576,'Zomato 3PO vs POS'!Z2:Z1048576,"<>",'Zomato 3PO vs POS'!AU2:AU1048576,"UNRECONCILED",'Zomato 3PO vs POS'!AX2:AX1048576,"TAX_PAID_BY_CUSTOMER_ZOMATO_POS_MISMATCH")
A22: Commission Value mismatch | B22: =COUNTIFS('Zomato POS vs 3PO'!AC2:AC1048576,"UNRECONCILED",'Zomato POS vs 3PO'!AF2:AF1048576,"COMMISSION_VALUE_ZOMATO_POS_MISMATCH") | C22: =SUMIFS('Zomato POS vs 3PO'!E2:E1048576,'Zomato POS vs 3PO'!E2:E1048576,"<>",'Zomato POS vs 3PO'!AC2:AC1048576,"UNRECONCILED",'Zomato POS vs 3PO'!AF2:AF1048576,"COMMISSION_VALUE_ZOMATO_POS_MISMATCH") | D22: =SUMIFS('Zomato POS vs 3PO'!F2:F1048576,'Zomato POS vs 3PO'!F2:F1048576,"<>",'Zomato POS vs 3PO'!AC2:AC1048576,"UNRECONCILED",'Zomato POS vs 3PO'!AF2:AF1048576,"COMMISSION_VALUE_ZOMATO_POS_MISMATCH") | E22: =C22-D22 | F22: =SUMIFS('Zomato POS vs 3PO'!Z2:Z1048576,'Zomato POS vs 3PO'!Z2:Z1048576,"<>",'Zomato POS vs 3PO'!AC2:AC1048576,"UNRECONCILED",'Zomato POS vs 3PO'!AF2:AF1048576,"COMMISSION_VALUE_ZOMATO_POS_MISMATCH") | G22: =COUNTIFS('Zomato 3PO vs POS'!AU2:AU1048576,"UNRECONCILED",'Zomato 3PO vs POS'!AX2:AX1048576,"COMMISSION_VALUE_ZOMATO_POS_MISMATCH") | H22: =SUMIFS('Zomato 3PO vs POS'!E2:E1048576,'Zomato 3PO vs POS'!E2:E1048576,"<>",'Zomato 3PO vs POS'!AU2:AU1048576,"UNRECONCILED",'Zomato 3PO vs POS'!AX2:AX1048576,"COMMISSION_VALUE_ZOMATO_POS_MISMATCH") | I22: =SUMIFS('Zomato 3PO vs POS'!F2:F1048576,'Zomato 3PO vs POS'!F2:F1048576,"<>",'Zomato 3PO vs POS'!AU2:AU1048576,"UNRECONCILED",'Zomato 3PO vs POS'!AX2:AX1048576,"COMMISSION_VALUE_ZOMATO_POS_MISMATCH") | J22: =H22-I22 | K22: =SUMIFS('Zomato 3PO vs POS'!Z2:Z1048576,'Zomato 3PO vs POS'!Z2:Z1048576,"<>",'Zomato 3PO vs POS'!AU2:AU1048576,"UNRECONCILED",'Zomato 3PO vs POS'!AX2:AX1048576,"COMMISSION_VALUE_ZOMATO_POS_MISMATCH")
A23: PG Charge mismatch | B23: =COUNTIFS('Zomato POS vs 3PO'!AC2:AC1048576,"UNRECONCILED",'Zomato POS vs 3PO'!AF2:AF1048576,"PG_CHARGE_ZOMATO_POS_MISMATCH") | C23: =SUMIFS('Zomato POS vs 3PO'!E2:E1048576,'Zomato POS vs 3PO'!E2:E1048576,"<>",'Zomato POS vs 3PO'!AC2:AC1048576,"UNRECONCILED",'Zomato POS vs 3PO'!AF2:AF1048576,"PG_CHARGE_ZOMATO_POS_MISMATCH") | D23: =SUMIFS('Zomato POS vs 3PO'!F2:F1048576,'Zomato POS vs 3PO'!F2:F1048576,"<>",'Zomato POS vs 3PO'!AC2:AC1048576,"UNRECONCILED",'Zomato POS vs 3PO'!AF2:AF1048576,"PG_CHARGE_ZOMATO_POS_MISMATCH") | E23: =C23-D23 | F23: =SUMIFS('Zomato POS vs 3PO'!Z2:Z1048576,'Zomato POS vs 3PO'!Z2:Z1048576,"<>",'Zomato POS vs 3PO'!AC2:AC1048576,"UNRECONCILED",'Zomato POS vs 3PO'!AF2:AF1048576,"PG_CHARGE_ZOMATO_POS_MISMATCH") | G23: =COUNTIFS('Zomato 3PO vs POS'!AU2:AU1048576,"UNRECONCILED",'Zomato 3PO vs POS'!AX2:AX1048576,"PG_CHARGE_ZOMATO_POS_MISMATCH") | H23: =SUMIFS('Zomato 3PO vs POS'!E2:E1048576,'Zomato 3PO vs POS'!E2:E1048576,"<>",'Zomato 3PO vs POS'!AU2:AU1048576,"UNRECONCILED",'Zomato 3PO vs POS'!AX2:AX1048576,"PG_CHARGE_ZOMATO_POS_MISMATCH") | I23: =SUMIFS('Zomato 3PO vs POS'!F2:F1048576,'Zomato 3PO vs POS'!F2:F1048576,"<>",'Zomato 3PO vs POS'!AU2:AU1048576,"UNRECONCILED",'Zomato 3PO vs POS'!AX2:AX1048576,"PG_CHARGE_ZOMATO_POS_MISMATCH") | J23: =H23-I23 | K23: =SUMIFS('Zomato 3PO vs POS'!Z2:Z1048576,'Zomato 3PO vs POS'!Z2:Z1048576,"<>",'Zomato 3PO vs POS'!AU2:AU1048576,"UNRECONCILED",'Zomato 3PO vs POS'!AX2:AX1048576,"PG_CHARGE_ZOMATO_POS_MISMATCH")
A24: Net Amount & Tax Paid by Customer mismatch | B24: =COUNTIFS('Zomato POS vs 3PO'!AC2:AC1048576,"UNRECONCILED",'Zomato POS vs 3PO'!AF2:AF1048576,"NET_AMOUNT_ZOMATO_POS_MISMATCH,TAX_PAID_BY_CUSTOMER_ZOMATO_POS_MISMATCH") | C24: =SUMIFS('Zomato POS vs 3PO'!E2:E1048576,'Zomato POS vs 3PO'!E2:E1048576,"<>",'Zomato POS vs 3PO'!AC2:AC1048576,"UNRECONCILED",'Zomato POS vs 3PO'!AF2:AF1048576,"NET_AMOUNT_ZOMATO_POS_MISMATCH,TAX_PAID_BY_CUSTOMER_ZOMATO_POS_MISMATCH") | D24: =SUMIFS('Zomato POS vs 3PO'!F2:F1048576,'Zomato POS vs 3PO'!F2:F1048576,"<>",'Zomato POS vs 3PO'!AC2:AC1048576,"UNRECONCILED",'Zomato POS vs 3PO'!AF2:AF1048576,"NET_AMOUNT_ZOMATO_POS_MISMATCH,TAX_PAID_BY_CUSTOMER_ZOMATO_POS_MISMATCH") | E24: =C24-D24 | F24: =SUMIFS('Zomato POS vs 3PO'!Z2:Z1048576,'Zomato POS vs 3PO'!Z2:Z1048576,"<>",'Zomato POS vs 3PO'!AC2:AC1048576,"UNRECONCILED",'Zomato POS vs 3PO'!AF2:AF1048576,"NET_AMOUNT_ZOMATO_POS_MISMATCH,TAX_PAID_BY_CUSTOMER_ZOMATO_POS_MISMATCH") | G24: =COUNTIFS('Zomato 3PO vs POS'!AU2:AU1048576,"UNRECONCILED",'Zomato 3PO vs POS'!AX2:AX1048576,"NET_AMOUNT_ZOMATO_POS_MISMATCH,TAX_PAID_BY_CUSTOMER_ZOMATO_POS_MISMATCH") | H24: =SUMIFS('Zomato 3PO vs POS'!E2:E1048576,'Zomato 3PO vs POS'!E2:E1048576,"<>",'Zomato 3PO vs POS'!AU2:AU1048576,"UNRECONCILED",'Zomato 3PO vs POS'!AX2:AX1048576,"NET_AMOUNT_ZOMATO_POS_MISMATCH,TAX_PAID_BY_CUSTOMER_ZOMATO_POS_MISMATCH") | I24: =SUMIFS('Zomato 3PO vs POS'!F2:F1048576,'Zomato 3PO vs POS'!F2:F1048576,"<>",'Zomato 3PO vs POS'!AU2:AU1048576,"UNRECONCILED",'Zomato 3PO vs POS'!AX2:AX1048576,"NET_AMOUNT_ZOMATO_POS_MISMATCH,TAX_PAID_BY_CUSTOMER_ZOMATO_POS_MISMATCH") | J24: =H24-I24 | K24: =SUMIFS('Zomato 3PO vs POS'!Z2:Z1048576,'Zomato 3PO vs POS'!Z2:Z1048576,"<>",'Zomato 3PO vs POS'!AU2:AU1048576,"UNRECONCILED",'Zomato 3PO vs POS'!AX2:AX1048576,"NET_AMOUNT_ZOMATO_POS_MISMATCH,TAX_PAID_BY_CUSTOMER_ZOMATO_POS_MISMATCH")
A25: Net Amount & Commission Value mismatch | B25: =COUNTIFS('Zomato POS vs 3PO'!AC2:AC1048576,"UNRECONCILED",'Zomato POS vs 3PO'!AF2:AF1048576,"NET_AMOUNT_ZOMATO_POS_MISMATCH,COMMISSION_VALUE_ZOMATO_POS_MISMATCH") | C25: =SUMIFS('Zomato POS vs 3PO'!E2:E1048576,'Zomato POS vs 3PO'!E2:E1048576,"<>",'Zomato POS vs 3PO'!AC2:AC1048576,"UNRECONCILED",'Zomato POS vs 3PO'!AF2:AF1048576,"NET_AMOUNT_ZOMATO_POS_MISMATCH,COMMISSION_VALUE_ZOMATO_POS_MISMATCH") | D25: =SUMIFS('Zomato POS vs 3PO'!F2:F1048576,'Zomato POS vs 3PO'!F2:F1048576,"<>",'Zomato POS vs 3PO'!AC2:AC1048576,"UNRECONCILED",'Zomato POS vs 3PO'!AF2:AF1048576,"NET_AMOUNT_ZOMATO_POS_MISMATCH,COMMISSION_VALUE_ZOMATO_POS_MISMATCH") | E25: =C25-D25 | F25: =SUMIFS('Zomato POS vs 3PO'!Z2:Z1048576,'Zomato POS vs 3PO'!Z2:Z1048576,"<>",'Zomato POS vs 3PO'!AC2:AC1048576,"UNRECONCILED",'Zomato POS vs 3PO'!AF2:AF1048576,"NET_AMOUNT_ZOMATO_POS_MISMATCH,COMMISSION_VALUE_ZOMATO_POS_MISMATCH") | G25: =COUNTIFS('Zomato 3PO vs POS'!AU2:AU1048576,"UNRECONCILED",'Zomato 3PO vs POS'!AX2:AX1048576,"NET_AMOUNT_ZOMATO_POS_MISMATCH,COMMISSION_VALUE_ZOMATO_POS_MISMATCH") | H25: =SUMIFS('Zomato 3PO vs POS'!E2:E1048576,'Zomato 3PO vs POS'!E2:E1048576,"<>",'Zomato 3PO vs POS'!AU2:AU1048576,"UNRECONCILED",'Zomato 3PO vs POS'!AX2:AX1048576,"NET_AMOUNT_ZOMATO_POS_MISMATCH,COMMISSION_VALUE_ZOMATO_POS_MISMATCH") | I25: =SUMIFS('Zomato 3PO vs POS'!F2:F1048576,'Zomato 3PO vs POS'!F2:F1048576,"<>",'Zomato 3PO vs POS'!AU2:AU1048576,"UNRECONCILED",'Zomato 3PO vs POS'!AX2:AX1048576,"NET_AMOUNT_ZOMATO_POS_MISMATCH,COMMISSION_VALUE_ZOMATO_POS_MISMATCH") | J25: =H25-I25 | K25: =SUMIFS('Zomato 3PO vs POS'!Z2:Z1048576,'Zomato 3PO vs POS'!Z2:Z1048576,"<>",'Zomato 3PO vs POS'!AU2:AU1048576,"UNRECONCILED",'Zomato 3PO vs POS'!AX2:AX1048576,"NET_AMOUNT_ZOMATO_POS_MISMATCH,COMMISSION_VALUE_ZOMATO_POS_MISMATCH")
A26: Net Amount & PG Charge mismatch | B26: =COUNTIFS('Zomato POS vs 3PO'!AC2:AC1048576,"UNRECONCILED",'Zomato POS vs 3PO'!AF2:AF1048576,"NET_AMOUNT_ZOMATO_POS_MISMATCH,PG_CHARGE_ZOMATO_POS_MISMATCH") | C26: =SUMIFS('Zomato POS vs 3PO'!E2:E1048576,'Zomato POS vs 3PO'!E2:E1048576,"<>",'Zomato POS vs 3PO'!AC2:AC1048576,"UNRECONCILED",'Zomato POS vs 3PO'!AF2:AF1048576,"NET_AMOUNT_ZOMATO_POS_MISMATCH,PG_CHARGE_ZOMATO_POS_MISMATCH") | D26: =SUMIFS('Zomato POS vs 3PO'!F2:F1048576,'Zomato POS vs 3PO'!F2:F1048576,"<>",'Zomato POS vs 3PO'!AC2:AC1048576,"UNRECONCILED",'Zomato POS vs 3PO'!AF2:AF1048576,"NET_AMOUNT_ZOMATO_POS_MISMATCH,PG_CHARGE_ZOMATO_POS_MISMATCH") | E26: =C26-D26 | F26: =SUMIFS('Zomato POS vs 3PO'!Z2:Z1048576,'Zomato POS vs 3PO'!Z2:Z1048576,"<>",'Zomato POS vs 3PO'!AC2:AC1048576,"UNRECONCILED",'Zomato POS vs 3PO'!AF2:AF1048576,"NET_AMOUNT_ZOMATO_POS_MISMATCH,PG_CHARGE_ZOMATO_POS_MISMATCH") | G26: =COUNTIFS('Zomato 3PO vs POS'!AU2:AU1048576,"UNRECONCILED",'Zomato 3PO vs POS'!AX2:AX1048576,"NET_AMOUNT_ZOMATO_POS_MISMATCH,PG_CHARGE_ZOMATO_POS_MISMATCH") | H26: =SUMIFS('Zomato 3PO vs POS'!E2:E1048576,'Zomato 3PO vs POS'!E2:E1048576,"<>",'Zomato 3PO vs POS'!AU2:AU1048576,"UNRECONCILED",'Zomato 3PO vs POS'!AX2:AX1048576,"NET_AMOUNT_ZOMATO_POS_MISMATCH,PG_CHARGE_ZOMATO_POS_MISMATCH") | I26: =SUMIFS('Zomato 3PO vs POS'!F2:F1048576,'Zomato 3PO vs POS'!F2:F1048576,"<>",'Zomato 3PO vs POS'!AU2:AU1048576,"UNRECONCILED",'Zomato 3PO vs POS'!AX2:AX1048576,"NET_AMOUNT_ZOMATO_POS_MISMATCH,PG_CHARGE_ZOMATO_POS_MISMATCH") | J26: =H26-I26 | K26: =SUMIFS('Zomato 3PO vs POS'!Z2:Z1048576,'Zomato 3PO vs POS'!Z2:Z1048576,"<>",'Zomato 3PO vs POS'!AU2:AU1048576,"UNRECONCILED",'Zomato 3PO vs POS'!AX2:AX1048576,"NET_AMOUNT_ZOMATO_POS_MISMATCH,PG_CHARGE_ZOMATO_POS_MISMATCH")
A27: Tax Paid by Customer & Commission Value mismatch | B27: =COUNTIFS('Zomato POS vs 3PO'!AC2:AC1048576,"UNRECONCILED",'Zomato POS vs 3PO'!AF2:AF1048576,"TAX_PAID_BY_CUSTOMER_ZOMATO_POS_MISMATCH,COMMISSION_VALUE_ZOMATO_POS_MISMATCH") | C27: =SUMIFS('Zomato POS vs 3PO'!E2:E1048576,'Zomato POS vs 3PO'!E2:E1048576,"<>",'Zomato POS vs 3PO'!AC2:AC1048576,"UNRECONCILED",'Zomato POS vs 3PO'!AF2:AF1048576,"TAX_PAID_BY_CUSTOMER_ZOMATO_POS_MISMATCH,COMMISSION_VALUE_ZOMATO_POS_MISMATCH") | D27: =SUMIFS('Zomato POS vs 3PO'!F2:F1048576,'Zomato POS vs 3PO'!F2:F1048576,"<>",'Zomato POS vs 3PO'!AC2:AC1048576,"UNRECONCILED",'Zomato POS vs 3PO'!AF2:AF1048576,"TAX_PAID_BY_CUSTOMER_ZOMATO_POS_MISMATCH,COMMISSION_VALUE_ZOMATO_POS_MISMATCH") | E27: =C27-D27 | F27: =SUMIFS('Zomato POS vs 3PO'!Z2:Z1048576,'Zomato POS vs 3PO'!Z2:Z1048576,"<>",'Zomato POS vs 3PO'!AC2:AC1048576,"UNRECONCILED",'Zomato POS vs 3PO'!AF2:AF1048576,"TAX_PAID_BY_CUSTOMER_ZOMATO_POS_MISMATCH,COMMISSION_VALUE_ZOMATO_POS_MISMATCH") | G27: =COUNTIFS('Zomato 3PO vs POS'!AU2:AU1048576,"UNRECONCILED",'Zomato 3PO vs POS'!AX2:AX1048576,"TAX_PAID_BY_CUSTOMER_ZOMATO_POS_MISMATCH,COMMISSION_VALUE_ZOMATO_POS_MISMATCH") | H27: =SUMIFS('Zomato 3PO vs POS'!E2:E1048576,'Zomato 3PO vs POS'!E2:E1048576,"<>",'Zomato 3PO vs POS'!AU2:AU1048576,"UNRECONCILED",'Zomato 3PO vs POS'!AX2:AX1048576,"TAX_PAID_BY_CUSTOMER_ZOMATO_POS_MISMATCH,COMMISSION_VALUE_ZOMATO_POS_MISMATCH") | I27: =SUMIFS('Zomato 3PO vs POS'!F2:F1048576,'Zomato 3PO vs POS'!F2:F1048576,"<>",'Zomato 3PO vs POS'!AU2:AU1048576,"UNRECONCILED",'Zomato 3PO vs POS'!AX2:AX1048576,"TAX_PAID_BY_CUSTOMER_ZOMATO_POS_MISMATCH,COMMISSION_VALUE_ZOMATO_POS_MISMATCH") | J27: =H27-I27 | K27: =SUMIFS('Zomato 3PO vs POS'!Z2:Z1048576,'Zomato 3PO vs POS'!Z2:Z1048576,"<>",'Zomato 3PO vs POS'!AU2:AU1048576,"UNRECONCILED",'Zomato 3PO vs POS'!AX2:AX1048576,"TAX_PAID_BY_CUSTOMER_ZOMATO_POS_MISMATCH,COMMISSION_VALUE_ZOMATO_POS_MISMATCH")
A28: Tax Paid by Customer & PG Charge mismatch | B28: =COUNTIFS('Zomato POS vs 3PO'!AC2:AC1048576,"UNRECONCILED",'Zomato POS vs 3PO'!AF2:AF1048576,"TAX_PAID_BY_CUSTOMER_ZOMATO_POS_MISMATCH,PG_CHARGE_ZOMATO_POS_MISMATCH") | C28: =SUMIFS('Zomato POS vs 3PO'!E2:E1048576,'Zomato POS vs 3PO'!E2:E1048576,"<>",'Zomato POS vs 3PO'!AC2:AC1048576,"UNRECONCILED",'Zomato POS vs 3PO'!AF2:AF1048576,"TAX_PAID_BY_CUSTOMER_ZOMATO_POS_MISMATCH,PG_CHARGE_ZOMATO_POS_MISMATCH") | D28: =SUMIFS('Zomato POS vs 3PO'!F2:F1048576,'Zomato POS vs 3PO'!F2:F1048576,"<>",'Zomato POS vs 3PO'!AC2:AC1048576,"UNRECONCILED",'Zomato POS vs 3PO'!AF2:AF1048576,"TAX_PAID_BY_CUSTOMER_ZOMATO_POS_MISMATCH,PG_CHARGE_ZOMATO_POS_MISMATCH") | E28: =C28-D28 | F28: =SUMIFS('Zomato POS vs 3PO'!Z2:Z1048576,'Zomato POS vs 3PO'!Z2:Z1048576,"<>",'Zomato POS vs 3PO'!AC2:AC1048576,"UNRECONCILED",'Zomato POS vs 3PO'!AF2:AF1048576,"TAX_PAID_BY_CUSTOMER_ZOMATO_POS_MISMATCH,PG_CHARGE_ZOMATO_POS_MISMATCH") | G28: =COUNTIFS('Zomato 3PO vs POS'!AU2:AU1048576,"UNRECONCILED",'Zomato 3PO vs POS'!AX2:AX1048576,"TAX_PAID_BY_CUSTOMER_ZOMATO_POS_MISMATCH,PG_CHARGE_ZOMATO_POS_MISMATCH") | H28: =SUMIFS('Zomato 3PO vs POS'!E2:E1048576,'Zomato 3PO vs POS'!E2:E1048576,"<>",'Zomato 3PO vs POS'!AU2:AU1048576,"UNRECONCILED",'Zomato 3PO vs POS'!AX2:AX1048576,"TAX_PAID_BY_CUSTOMER_ZOMATO_POS_MISMATCH,PG_CHARGE_ZOMATO_POS_MISMATCH") | I28: =SUMIFS('Zomato 3PO vs POS'!F2:F1048576,'Zomato 3PO vs POS'!F2:F1048576,"<>",'Zomato 3PO vs POS'!AU2:AU1048576,"UNRECONCILED",'Zomato 3PO vs POS'!AX2:AX1048576,"TAX_PAID_BY_CUSTOMER_ZOMATO_POS_MISMATCH,PG_CHARGE_ZOMATO_POS_MISMATCH") | J28: =H28-I28 | K28: =SUMIFS('Zomato 3PO vs POS'!Z2:Z1048576,'Zomato 3PO vs POS'!Z2:Z1048576,"<>",'Zomato 3PO vs POS'!AU2:AU1048576,"UNRECONCILED",'Zomato 3PO vs POS'!AX2:AX1048576,"TAX_PAID_BY_CUSTOMER_ZOMATO_POS_MISMATCH,PG_CHARGE_ZOMATO_POS_MISMATCH")
A29: Commission Value & PG Charge mismatch | B29: =COUNTIFS('Zomato POS vs 3PO'!AC2:AC1048576,"UNRECONCILED",'Zomato POS vs 3PO'!AF2:AF1048576,"COMMISSION_VALUE_ZOMATO_POS_MISMATCH,PG_CHARGE_ZOMATO_POS_MISMATCH") | C29: =SUMIFS('Zomato POS vs 3PO'!E2:E1048576,'Zomato POS vs 3PO'!E2:E1048576,"<>",'Zomato POS vs 3PO'!AC2:AC1048576,"UNRECONCILED",'Zomato POS vs 3PO'!AF2:AF1048576,"COMMISSION_VALUE_ZOMATO_POS_MISMATCH,PG_CHARGE_ZOMATO_POS_MISMATCH") | D29: =SUMIFS('Zomato POS vs 3PO'!F2:F1048576,'Zomato POS vs 3PO'!F2:F1048576,"<>",'Zomato POS vs 3PO'!AC2:AC1048576,"UNRECONCILED",'Zomato POS vs 3PO'!AF2:AF1048576,"COMMISSION_VALUE_ZOMATO_POS_MISMATCH,PG_CHARGE_ZOMATO_POS_MISMATCH") | E29: =C29-D29 | F29: =SUMIFS('Zomato POS vs 3PO'!Z2:Z1048576,'Zomato POS vs 3PO'!Z2:Z1048576,"<>",'Zomato POS vs 3PO'!AC2:AC1048576,"UNRECONCILED",'Zomato POS vs 3PO'!AF2:AF1048576,"COMMISSION_VALUE_ZOMATO_POS_MISMATCH,PG_CHARGE_ZOMATO_POS_MISMATCH") | G29: =COUNTIFS('Zomato 3PO vs POS'!AU2:AU1048576,"UNRECONCILED",'Zomato 3PO vs POS'!AX2:AX1048576,"COMMISSION_VALUE_ZOMATO_POS_MISMATCH,PG_CHARGE_ZOMATO_POS_MISMATCH") | H29: =SUMIFS('Zomato 3PO vs POS'!E2:E1048576,'Zomato 3PO vs POS'!E2:E1048576,"<>",'Zomato 3PO vs POS'!AU2:AU1048576,"UNRECONCILED",'Zomato 3PO vs POS'!AX2:AX1048576,"COMMISSION_VALUE_ZOMATO_POS_MISMATCH,PG_CHARGE_ZOMATO_POS_MISMATCH") | I29: =SUMIFS('Zomato 3PO vs POS'!F2:F1048576,'Zomato 3PO vs POS'!F2:F1048576,"<>",'Zomato 3PO vs POS'!AU2:AU1048576,"UNRECONCILED",'Zomato 3PO vs POS'!AX2:AX1048576,"COMMISSION_VALUE_ZOMATO_POS_MISMATCH,PG_CHARGE_ZOMATO_POS_MISMATCH") | J29: =H29-I29 | K29: =SUMIFS('Zomato 3PO vs POS'!Z2:Z1048576,'Zomato 3PO vs POS'!Z2:Z1048576,"<>",'Zomato 3PO vs POS'!AU2:AU1048576,"UNRECONCILED",'Zomato 3PO vs POS'!AX2:AX1048576,"COMMISSION_VALUE_ZOMATO_POS_MISMATCH,PG_CHARGE_ZOMATO_POS_MISMATCH")
A30: Net Amount, Tax Paid by Customer & Commission Value mismatch | B30: =COUNTIFS('Zomato POS vs 3PO'!AC2:AC1048576,"UNRECONCILED",'Zomato POS vs 3PO'!AF2:AF1048576,"NET_AMOUNT_ZOMATO_POS_MISMATCH,TAX_PAID_BY_CUSTOMER_ZOMATO_POS_MISMATCH,COMMISSION_VALUE_ZOMATO_POS_MISMATCH") | C30: =SUMIFS('Zomato POS vs 3PO'!E2:E1048576,'Zomato POS vs 3PO'!E2:E1048576,"<>",'Zomato POS vs 3PO'!AC2:AC1048576,"UNRECONCILED",'Zomato POS vs 3PO'!AF2:AF1048576,"NET_AMOUNT_ZOMATO_POS_MISMATCH,TAX_PAID_BY_CUSTOMER_ZOMATO_POS_MISMATCH,COMMISSION_VALUE_ZOMATO_POS_MISMATCH") | D30: =SUMIFS('Zomato POS vs 3PO'!F2:F1048576,'Zomato POS vs 3PO'!F2:F1048576,"<>",'Zomato POS vs 3PO'!AC2:AC1048576,"UNRECONCILED",'Zomato POS vs 3PO'!AF2:AF1048576,"NET_AMOUNT_ZOMATO_POS_MISMATCH,TAX_PAID_BY_CUSTOMER_ZOMATO_POS_MISMATCH,COMMISSION_VALUE_ZOMATO_POS_MISMATCH") | E30: =C30-D30 | F30: =SUMIFS('Zomato POS vs 3PO'!Z2:Z1048576,'Zomato POS vs 3PO'!Z2:Z1048576,"<>",'Zomato POS vs 3PO'!AC2:AC1048576,"UNRECONCILED",'Zomato POS vs 3PO'!AF2:AF1048576,"NET_AMOUNT_ZOMATO_POS_MISMATCH,TAX_PAID_BY_CUSTOMER_ZOMATO_POS_MISMATCH,COMMISSION_VALUE_ZOMATO_POS_MISMATCH") | G30: =COUNTIFS('Zomato 3PO vs POS'!AU2:AU1048576,"UNRECONCILED",'Zomato 3PO vs POS'!AX2:AX1048576,"NET_AMOUNT_ZOMATO_POS_MISMATCH,TAX_PAID_BY_CUSTOMER_ZOMATO_POS_MISMATCH,COMMISSION_VALUE_ZOMATO_POS_MISMATCH") | H30: =SUMIFS('Zomato 3PO vs POS'!E2:E1048576,'Zomato 3PO vs POS'!E2:E1048576,"<>",'Zomato 3PO vs POS'!AU2:AU1048576,"UNRECONCILED",'Zomato 3PO vs POS'!AX2:AX1048576,"NET_AMOUNT_ZOMATO_POS_MISMATCH,TAX_PAID_BY_CUSTOMER_ZOMATO_POS_MISMATCH,COMMISSION_VALUE_ZOMATO_POS_MISMATCH") | I30: =SUMIFS('Zomato 3PO vs POS'!F2:F1048576,'Zomato 3PO vs POS'!F2:F1048576,"<>",'Zomato 3PO vs POS'!AU2:AU1048576,"UNRECONCILED",'Zomato 3PO vs POS'!AX2:AX1048576,"NET_AMOUNT_ZOMATO_POS_MISMATCH,TAX_PAID_BY_CUSTOMER_ZOMATO_POS_MISMATCH,COMMISSION_VALUE_ZOMATO_POS_MISMATCH") | J30: =H30-I30 | K30: =SUMIFS('Zomato 3PO vs POS'!Z2:Z1048576,'Zomato 3PO vs POS'!Z2:Z1048576,"<>",'Zomato 3PO vs POS'!AU2:AU1048576,"UNRECONCILED",'Zomato 3PO vs POS'!AX2:AX1048576,"NET_AMOUNT_ZOMATO_POS_MISMATCH,TAX_PAID_BY_CUSTOMER_ZOMATO_POS_MISMATCH,COMMISSION_VALUE_ZOMATO_POS_MISMATCH")
A31: Net Amount, Tax Paid by Customer & PG Charge mismatch | B31: =COUNTIFS('Zomato POS vs 3PO'!AC2:AC1048576,"UNRECONCILED",'Zomato POS vs 3PO'!AF2:AF1048576,"NET_AMOUNT_ZOMATO_POS_MISMATCH,TAX_PAID_BY_CUSTOMER_ZOMATO_POS_MISMATCH,PG_CHARGE_ZOMATO_POS_MISMATCH") | C31: =SUMIFS('Zomato POS vs 3PO'!E2:E1048576,'Zomato POS vs 3PO'!E2:E1048576,"<>",'Zomato POS vs 3PO'!AC2:AC1048576,"UNRECONCILED",'Zomato POS vs 3PO'!AF2:AF1048576,"NET_AMOUNT_ZOMATO_POS_MISMATCH,TAX_PAID_BY_CUSTOMER_ZOMATO_POS_MISMATCH,PG_CHARGE_ZOMATO_POS_MISMATCH") | D31: =SUMIFS('Zomato POS vs 3PO'!F2:F1048576,'Zomato POS vs 3PO'!F2:F1048576,"<>",'Zomato POS vs 3PO'!AC2:AC1048576,"UNRECONCILED",'Zomato POS vs 3PO'!AF2:AF1048576,"NET_AMOUNT_ZOMATO_POS_MISMATCH,TAX_PAID_BY_CUSTOMER_ZOMATO_POS_MISMATCH,PG_CHARGE_ZOMATO_POS_MISMATCH") | E31: =C31-D31 | F31: =SUMIFS('Zomato POS vs 3PO'!Z2:Z1048576,'Zomato POS vs 3PO'!Z2:Z1048576,"<>",'Zomato POS vs 3PO'!AC2:AC1048576,"UNRECONCILED",'Zomato POS vs 3PO'!AF2:AF1048576,"NET_AMOUNT_ZOMATO_POS_MISMATCH,TAX_PAID_BY_CUSTOMER_ZOMATO_POS_MISMATCH,PG_CHARGE_ZOMATO_POS_MISMATCH") | G31: =COUNTIFS('Zomato 3PO vs POS'!AU2:AU1048576,"UNRECONCILED",'Zomato 3PO vs POS'!AX2:AX1048576,"NET_AMOUNT_ZOMATO_POS_MISMATCH,TAX_PAID_BY_CUSTOMER_ZOMATO_POS_MISMATCH,PG_CHARGE_ZOMATO_POS_MISMATCH") | H31: =SUMIFS('Zomato 3PO vs POS'!E2:E1048576,'Zomato 3PO vs POS'!E2:E1048576,"<>",'Zomato 3PO vs POS'!AU2:AU1048576,"UNRECONCILED",'Zomato 3PO vs POS'!AX2:AX1048576,"NET_AMOUNT_ZOMATO_POS_MISMATCH,TAX_PAID_BY_CUSTOMER_ZOMATO_POS_MISMATCH,PG_CHARGE_ZOMATO_POS_MISMATCH") | I31: =SUMIFS('Zomato 3PO vs POS'!F2:F1048576,'Zomato 3PO vs POS'!F2:F1048576,"<>",'Zomato 3PO vs POS'!AU2:AU1048576,"UNRECONCILED",'Zomato 3PO vs POS'!AX2:AX1048576,"NET_AMOUNT_ZOMATO_POS_MISMATCH,TAX_PAID_BY_CUSTOMER_ZOMATO_POS_MISMATCH,PG_CHARGE_ZOMATO_POS_MISMATCH") | J31: =H31-I31 | K31: =SUMIFS('Zomato 3PO vs POS'!Z2:Z1048576,'Zomato 3PO vs POS'!Z2:Z1048576,"<>",'Zomato 3PO vs POS'!AU2:AU1048576,"UNRECONCILED",'Zomato 3PO vs POS'!AX2:AX1048576,"NET_AMOUNT_ZOMATO_POS_MISMATCH,TAX_PAID_BY_CUSTOMER_ZOMATO_POS_MISMATCH,PG_CHARGE_ZOMATO_POS_MISMATCH")
A32: Net Amount, Commission Value & PG Charge mismatch | B32: =COUNTIFS('Zomato POS vs 3PO'!AC2:AC1048576,"UNRECONCILED",'Zomato POS vs 3PO'!AF2:AF1048576,"NET_AMOUNT_ZOMATO_POS_MISMATCH,COMMISSION_VALUE_ZOMATO_POS_MISMATCH,PG_CHARGE_ZOMATO_POS_MISMATCH") | C32: =SUMIFS('Zomato POS vs 3PO'!E2:E1048576,'Zomato POS vs 3PO'!E2:E1048576,"<>",'Zomato POS vs 3PO'!AC2:AC1048576,"UNRECONCILED",'Zomato POS vs 3PO'!AF2:AF1048576,"NET_AMOUNT_ZOMATO_POS_MISMATCH,COMMISSION_VALUE_ZOMATO_POS_MISMATCH,PG_CHARGE_ZOMATO_POS_MISMATCH") | D32: =SUMIFS('Zomato POS vs 3PO'!F2:F1048576,'Zomato POS vs 3PO'!F2:F1048576,"<>",'Zomato POS vs 3PO'!AC2:AC1048576,"UNRECONCILED",'Zomato POS vs 3PO'!AF2:AF1048576,"NET_AMOUNT_ZOMATO_POS_MISMATCH,COMMISSION_VALUE_ZOMATO_POS_MISMATCH,PG_CHARGE_ZOMATO_POS_MISMATCH") | E32: =C32-D32 | F32: =SUMIFS('Zomato POS vs 3PO'!Z2:Z1048576,'Zomato POS vs 3PO'!Z2:Z1048576,"<>",'Zomato POS vs 3PO'!AC2:AC1048576,"UNRECONCILED",'Zomato POS vs 3PO'!AF2:AF1048576,"NET_AMOUNT_ZOMATO_POS_MISMATCH,COMMISSION_VALUE_ZOMATO_POS_MISMATCH,PG_CHARGE_ZOMATO_POS_MISMATCH") | G32: =COUNTIFS('Zomato 3PO vs POS'!AU2:AU1048576,"UNRECONCILED",'Zomato 3PO vs POS'!AX2:AX1048576,"NET_AMOUNT_ZOMATO_POS_MISMATCH,COMMISSION_VALUE_ZOMATO_POS_MISMATCH,PG_CHARGE_ZOMATO_POS_MISMATCH") | H32: =SUMIFS('Zomato 3PO vs POS'!E2:E1048576,'Zomato 3PO vs POS'!E2:E1048576,"<>",'Zomato 3PO vs POS'!AU2:AU1048576,"UNRECONCILED",'Zomato 3PO vs POS'!AX2:AX1048576,"NET_AMOUNT_ZOMATO_POS_MISMATCH,COMMISSION_VALUE_ZOMATO_POS_MISMATCH,PG_CHARGE_ZOMATO_POS_MISMATCH") | I32: =SUMIFS('Zomato 3PO vs POS'!F2:F1048576,'Zomato 3PO vs POS'!F2:F1048576,"<>",'Zomato 3PO vs POS'!AU2:AU1048576,"UNRECONCILED",'Zomato 3PO vs POS'!AX2:AX1048576,"NET_AMOUNT_ZOMATO_POS_MISMATCH,COMMISSION_VALUE_ZOMATO_POS_MISMATCH,PG_CHARGE_ZOMATO_POS_MISMATCH") | J32: =H32-I32 | K32: =SUMIFS('Zomato 3PO vs POS'!Z2:Z1048576,'Zomato 3PO vs POS'!Z2:Z1048576,"<>",'Zomato 3PO vs POS'!AU2:AU1048576,"UNRECONCILED",'Zomato 3PO vs POS'!AX2:AX1048576,"NET_AMOUNT_ZOMATO_POS_MISMATCH,COMMISSION_VALUE_ZOMATO_POS_MISMATCH,PG_CHARGE_ZOMATO_POS_MISMATCH")
A33: Tax Paid by Customer, Commission Value & PG Charge mismatch | B33: =COUNTIFS('Zomato POS vs 3PO'!AC2:AC1048576,"UNRECONCILED",'Zomato POS vs 3PO'!AF2:AF1048576,"TAX_PAID_BY_CUSTOMER_ZOMATO_POS_MISMATCH,COMMISSION_VALUE_ZOMATO_POS_MISMATCH,PG_CHARGE_ZOMATO_POS_MISMATCH") | C33: =SUMIFS('Zomato POS vs 3PO'!E2:E1048576,'Zomato POS vs 3PO'!E2:E1048576,"<>",'Zomato POS vs 3PO'!AC2:AC1048576,"UNRECONCILED",'Zomato POS vs 3PO'!AF2:AF1048576,"TAX_PAID_BY_CUSTOMER_ZOMATO_POS_MISMATCH,COMMISSION_VALUE_ZOMATO_POS_MISMATCH,PG_CHARGE_ZOMATO_POS_MISMATCH") | D33: =SUMIFS('Zomato POS vs 3PO'!F2:F1048576,'Zomato POS vs 3PO'!F2:F1048576,"<>",'Zomato POS vs 3PO'!AC2:AC1048576,"UNRECONCILED",'Zomato POS vs 3PO'!AF2:AF1048576,"TAX_PAID_BY_CUSTOMER_ZOMATO_POS_MISMATCH,COMMISSION_VALUE_ZOMATO_POS_MISMATCH,PG_CHARGE_ZOMATO_POS_MISMATCH") | E33: =C33-D33 | F33: =SUMIFS('Zomato POS vs 3PO'!Z2:Z1048576,'Zomato POS vs 3PO'!Z2:Z1048576,"<>",'Zomato POS vs 3PO'!AC2:AC1048576,"UNRECONCILED",'Zomato POS vs 3PO'!AF2:AF1048576,"TAX_PAID_BY_CUSTOMER_ZOMATO_POS_MISMATCH,COMMISSION_VALUE_ZOMATO_POS_MISMATCH,PG_CHARGE_ZOMATO_POS_MISMATCH") | G33: =COUNTIFS('Zomato 3PO vs POS'!AU2:AU1048576,"UNRECONCILED",'Zomato 3PO vs POS'!AX2:AX1048576,"TAX_PAID_BY_CUSTOMER_ZOMATO_POS_MISMATCH,COMMISSION_VALUE_ZOMATO_POS_MISMATCH,PG_CHARGE_ZOMATO_POS_MISMATCH") | H33: =SUMIFS('Zomato 3PO vs POS'!E2:E1048576,'Zomato 3PO vs POS'!E2:E1048576,"<>",'Zomato 3PO vs POS'!AU2:AU1048576,"UNRECONCILED",'Zomato 3PO vs POS'!AX2:AX1048576,"TAX_PAID_BY_CUSTOMER_ZOMATO_POS_MISMATCH,COMMISSION_VALUE_ZOMATO_POS_MISMATCH,PG_CHARGE_ZOMATO_POS_MISMATCH") | I33: =SUMIFS('Zomato 3PO vs POS'!F2:F1048576,'Zomato 3PO vs POS'!F2:F1048576,"<>",'Zomato 3PO vs POS'!AU2:AU1048576,"UNRECONCILED",'Zomato 3PO vs POS'!AX2:AX1048576,"TAX_PAID_BY_CUSTOMER_ZOMATO_POS_MISMATCH,COMMISSION_VALUE_ZOMATO_POS_MISMATCH,PG_CHARGE_ZOMATO_POS_MISMATCH") | J33: =H33-I33 | K33: =SUMIFS('Zomato 3PO vs POS'!Z2:Z1048576,'Zomato 3PO vs POS'!Z2:Z1048576,"<>",'Zomato 3PO vs POS'!AU2:AU1048576,"UNRECONCILED",'Zomato 3PO vs POS'!AX2:AX1048576,"TAX_PAID_BY_CUSTOMER_ZOMATO_POS_MISMATCH,COMMISSION_VALUE_ZOMATO_POS_MISMATCH,PG_CHARGE_ZOMATO_POS_MISMATCH")
A34: Net Amount, Tax Paid by Customer, Commission Value & PG Charge mismatch | B34: =COUNTIFS('Zomato POS vs 3PO'!AC2:AC1048576,"UNRECONCILED",'Zomato POS vs 3PO'!AF2:AF1048576,"NET_AMOUNT_ZOMATO_POS_MISMATCH,TAX_PAID_BY_CUSTOMER_ZOMATO_POS_MISMATCH,COMMISSION_VALUE_ZOMATO_POS_MISMATCH,PG_CHARGE_ZOMATO_POS_MISMATCH") | C34: =SUMIFS('Zomato POS vs 3PO'!E2:E1048576,'Zomato POS vs 3PO'!E2:E1048576,"<>",'Zomato POS vs 3PO'!AC2:AC1048576,"UNRECONCILED",'Zomato POS vs 3PO'!AF2:AF1048576,"NET_AMOUNT_ZOMATO_POS_MISMATCH,TAX_PAID_BY_CUSTOMER_ZOMATO_POS_MISMATCH,COMMISSION_VALUE_ZOMATO_POS_MISMATCH,PG_CHARGE_ZOMATO_POS_MISMATCH") | D34: =SUMIFS('Zomato POS vs 3PO'!F2:F1048576,'Zomato POS vs 3PO'!F2:F1048576,"<>",'Zomato POS vs 3PO'!AC2:AC1048576,"UNRECONCILED",'Zomato POS vs 3PO'!AF2:AF1048576,"NET_AMOUNT_ZOMATO_POS_MISMATCH,TAX_PAID_BY_CUSTOMER_ZOMATO_POS_MISMATCH,COMMISSION_VALUE_ZOMATO_POS_MISMATCH,PG_CHARGE_ZOMATO_POS_MISMATCH") | E34: =C34-D34 | F34: =SUMIFS('Zomato POS vs 3PO'!Z2:Z1048576,'Zomato POS vs 3PO'!Z2:Z1048576,"<>",'Zomato POS vs 3PO'!AC2:AC1048576,"UNRECONCILED",'Zomato POS vs 3PO'!AF2:AF1048576,"NET_AMOUNT_ZOMATO_POS_MISMATCH,TAX_PAID_BY_CUSTOMER_ZOMATO_POS_MISMATCH,COMMISSION_VALUE_ZOMATO_POS_MISMATCH,PG_CHARGE_ZOMATO_POS_MISMATCH") | G34: =COUNTIFS('Zomato 3PO vs POS'!AU2:AU1048576,"UNRECONCILED",'Zomato 3PO vs POS'!AX2:AX1048576,"NET_AMOUNT_ZOMATO_POS_MISMATCH,TAX_PAID_BY_CUSTOMER_ZOMATO_POS_MISMATCH,COMMISSION_VALUE_ZOMATO_POS_MISMATCH,PG_CHARGE_ZOMATO_POS_MISMATCH") | H34: =SUMIFS('Zomato 3PO vs POS'!E2:E1048576,'Zomato 3PO vs POS'!E2:E1048576,"<>",'Zomato 3PO vs POS'!AU2:AU1048576,"UNRECONCILED",'Zomato 3PO vs POS'!AX2:AX1048576,"NET_AMOUNT_ZOMATO_POS_MISMATCH,TAX_PAID_BY_CUSTOMER_ZOMATO_POS_MISMATCH,COMMISSION_VALUE_ZOMATO_POS_MISMATCH,PG_CHARGE_ZOMATO_POS_MISMATCH") | I34: =SUMIFS('Zomato 3PO vs POS'!F2:F1048576,'Zomato 3PO vs POS'!F2:F1048576,"<>",'Zomato 3PO vs POS'!AU2:AU1048576,"UNRECONCILED",'Zomato 3PO vs POS'!AX2:AX1048576,"NET_AMOUNT_ZOMATO_POS_MISMATCH,TAX_PAID_BY_CUSTOMER_ZOMATO_POS_MISMATCH,COMMISSION_VALUE_ZOMATO_POS_MISMATCH,PG_CHARGE_ZOMATO_POS_MISMATCH") | J34: =H34-I34 | K34: =SUMIFS('Zomato 3PO vs POS'!Z2:Z1048576,'Zomato 3PO vs POS'!Z2:Z1048576,"<>",'Zomato 3PO vs POS'!AU2:AU1048576,"UNRECONCILED",'Zomato 3PO vs POS'!AX2:AX1048576,"NET_AMOUNT_ZOMATO_POS_MISMATCH,TAX_PAID_BY_CUSTOMER_ZOMATO_POS_MISMATCH,COMMISSION_VALUE_ZOMATO_POS_MISMATCH,PG_CHARGE_ZOMATO_POS_MISMATCH")
A35: PG Applied On mismatch | B35: =COUNTIFS('Zomato POS vs 3PO'!AC2:AC1048576,"UNRECONCILED",'Zomato POS vs 3PO'!AF2:AF1048576,"PG_APPLIED_ON_ZOMATO_POS_MISMATCH") | C35: =SUMIFS('Zomato POS vs 3PO'!E2:E1048576,'Zomato POS vs 3PO'!E2:E1048576,"<>",'Zomato POS vs 3PO'!AC2:AC1048576,"UNRECONCILED",'Zomato POS vs 3PO'!AF2:AF1048576,"PG_APPLIED_ON_ZOMATO_POS_MISMATCH") | D35: =SUMIFS('Zomato POS vs 3PO'!F2:F1048576,'Zomato POS vs 3PO'!F2:F1048576,"<>",'Zomato POS vs 3PO'!AC2:AC1048576,"UNRECONCILED",'Zomato POS vs 3PO'!AF2:AF1048576,"PG_APPLIED_ON_ZOMATO_POS_MISMATCH") | E35: =C35-D35 | F35: =SUMIFS('Zomato POS vs 3PO'!Z2:Z1048576,'Zomato POS vs 3PO'!Z2:Z1048576,"<>",'Zomato POS vs 3PO'!AC2:AC1048576,"UNRECONCILED",'Zomato POS vs 3PO'!AF2:AF1048576,"PG_APPLIED_ON_ZOMATO_POS_MISMATCH") | G35: =COUNTIFS('Zomato 3PO vs POS'!AU2:AU1048576,"UNRECONCILED",'Zomato 3PO vs POS'!AX2:AX1048576,"PG_APPLIED_ON_ZOMATO_POS_MISMATCH") | H35: =SUMIFS('Zomato 3PO vs POS'!E2:E1048576,'Zomato 3PO vs POS'!E2:E1048576,"<>",'Zomato 3PO vs POS'!AU2:AU1048576,"UNRECONCILED",'Zomato 3PO vs POS'!AX2:AX1048576,"PG_APPLIED_ON_ZOMATO_POS_MISMATCH") | I35: =SUMIFS('Zomato 3PO vs POS'!F2:F1048576,'Zomato 3PO vs POS'!F2:F1048576,"<>",'Zomato 3PO vs POS'!AU2:AU1048576,"UNRECONCILED",'Zomato 3PO vs POS'!AX2:AX1048576,"PG_APPLIED_ON_ZOMATO_POS_MISMATCH") | J35: =H35-I35 | K35: =SUMIFS('Zomato 3PO vs POS'!Z2:Z1048576,'Zomato 3PO vs POS'!Z2:Z1048576,"<>",'Zomato 3PO vs POS'!AU2:AU1048576,"UNRECONCILED",'Zomato 3PO vs POS'!AX2:AX1048576,"PG_APPLIED_ON_ZOMATO_POS_MISMATCH")
A36: Taxes Zomato Fee mismatch | B36: =COUNTIFS('Zomato POS vs 3PO'!AC2:AC1048576,"UNRECONCILED",'Zomato POS vs 3PO'!AF2:AF1048576,"TAXES_ZOMATO_FEE_ZOMATO_POS_MISMATCH") | C36: =SUMIFS('Zomato POS vs 3PO'!E2:E1048576,'Zomato POS vs 3PO'!E2:E1048576,"<>",'Zomato POS vs 3PO'!AC2:AC1048576,"UNRECONCILED",'Zomato POS vs 3PO'!AF2:AF1048576,"TAXES_ZOMATO_FEE_ZOMATO_POS_MISMATCH") | D36: =SUMIFS('Zomato POS vs 3PO'!F2:F1048576,'Zomato POS vs 3PO'!F2:F1048576,"<>",'Zomato POS vs 3PO'!AC2:AC1048576,"UNRECONCILED",'Zomato POS vs 3PO'!AF2:AF1048576,"TAXES_ZOMATO_FEE_ZOMATO_POS_MISMATCH") | E36: =C36-D36 | F36: =SUMIFS('Zomato POS vs 3PO'!Z2:Z1048576,'Zomato POS vs 3PO'!Z2:Z1048576,"<>",'Zomato POS vs 3PO'!AC2:AC1048576,"UNRECONCILED",'Zomato POS vs 3PO'!AF2:AF1048576,"TAXES_ZOMATO_FEE_ZOMATO_POS_MISMATCH") | G36: =COUNTIFS('Zomato 3PO vs POS'!AU2:AU1048576,"UNRECONCILED",'Zomato 3PO vs POS'!AX2:AX1048576,"TAXES_ZOMATO_FEE_ZOMATO_POS_MISMATCH") | H36: =SUMIFS('Zomato 3PO vs POS'!E2:E1048576,'Zomato 3PO vs POS'!E2:E1048576,"<>",'Zomato 3PO vs POS'!AU2:AU1048576,"UNRECONCILED",'Zomato 3PO vs POS'!AX2:AX1048576,"TAXES_ZOMATO_FEE_ZOMATO_POS_MISMATCH") | I36: =SUMIFS('Zomato 3PO vs POS'!F2:F1048576,'Zomato 3PO vs POS'!F2:F1048576,"<>",'Zomato 3PO vs POS'!AU2:AU1048576,"UNRECONCILED",'Zomato 3PO vs POS'!AX2:AX1048576,"TAXES_ZOMATO_FEE_ZOMATO_POS_MISMATCH") | J36: =H36-I36 | K36: =SUMIFS('Zomato 3PO vs POS'!Z2:Z1048576,'Zomato 3PO vs POS'!Z2:Z1048576,"<>",'Zomato 3PO vs POS'!AU2:AU1048576,"UNRECONCILED",'Zomato 3PO vs POS'!AX2:AX1048576,"TAXES_ZOMATO_FEE_ZOMATO_POS_MISMATCH")
A37: TDS Amount mismatch | B37: =COUNTIFS('Zomato POS vs 3PO'!AC2:AC1048576,"UNRECONCILED",'Zomato POS vs 3PO'!AF2:AF1048576,"TDS_AMOUNT_ZOMATO_POS_MISMATCH") | C37: =SUMIFS('Zomato POS vs 3PO'!E2:E1048576,'Zomato POS vs 3PO'!E2:E1048576,"<>",'Zomato POS vs 3PO'!AC2:AC1048576,"UNRECONCILED",'Zomato POS vs 3PO'!AF2:AF1048576,"TDS_AMOUNT_ZOMATO_POS_MISMATCH") | D37: =SUMIFS('Zomato POS vs 3PO'!F2:F1048576,'Zomato POS vs 3PO'!F2:F1048576,"<>",'Zomato POS vs 3PO'!AC2:AC1048576,"UNRECONCILED",'Zomato POS vs 3PO'!AF2:AF1048576,"TDS_AMOUNT_ZOMATO_POS_MISMATCH") | E37: =C37-D37 | F37: =SUMIFS('Zomato POS vs 3PO'!Z2:Z1048576,'Zomato POS vs 3PO'!Z2:Z1048576,"<>",'Zomato POS vs 3PO'!AC2:AC1048576,"UNRECONCILED",'Zomato POS vs 3PO'!AF2:AF1048576,"TDS_AMOUNT_ZOMATO_POS_MISMATCH") | G37: =COUNTIFS('Zomato 3PO vs POS'!AU2:AU1048576,"UNRECONCILED",'Zomato 3PO vs POS'!AX2:AX1048576,"TDS_AMOUNT_ZOMATO_POS_MISMATCH") | H37: =SUMIFS('Zomato 3PO vs POS'!E2:E1048576,'Zomato 3PO vs POS'!E2:E1048576,"<>",'Zomato 3PO vs POS'!AU2:AU1048576,"UNRECONCILED",'Zomato 3PO vs POS'!AX2:AX1048576,"TDS_AMOUNT_ZOMATO_POS_MISMATCH") | I37: =SUMIFS('Zomato 3PO vs POS'!F2:F1048576,'Zomato 3PO vs POS'!F2:F1048576,"<>",'Zomato 3PO vs POS'!AU2:AU1048576,"UNRECONCILED",'Zomato 3PO vs POS'!AX2:AX1048576,"TDS_AMOUNT_ZOMATO_POS_MISMATCH") | J37: =H37-I37 | K37: =SUMIFS('Zomato 3PO vs POS'!Z2:Z1048576,'Zomato 3PO vs POS'!Z2:Z1048576,"<>",'Zomato 3PO vs POS'!AU2:AU1048576,"UNRECONCILED",'Zomato 3PO vs POS'!AX2:AX1048576,"TDS_AMOUNT_ZOMATO_POS_MISMATCH")
A38: Final Amount mismatch | B38: =COUNTIFS('Zomato POS vs 3PO'!AC2:AC1048576,"UNRECONCILED",'Zomato POS vs 3PO'!AF2:AF1048576,"FINAL_AMOUNT_ZOMATO_POS_MISMATCH") | C38: =SUMIFS('Zomato POS vs 3PO'!E2:E1048576,'Zomato POS vs 3PO'!E2:E1048576,"<>",'Zomato POS vs 3PO'!AC2:AC1048576,"UNRECONCILED",'Zomato POS vs 3PO'!AF2:AF1048576,"FINAL_AMOUNT_ZOMATO_POS_MISMATCH") | D38: =SUMIFS('Zomato POS vs 3PO'!F2:F1048576,'Zomato POS vs 3PO'!F2:F1048576,"<>",'Zomato POS vs 3PO'!AC2:AC1048576,"UNRECONCILED",'Zomato POS vs 3PO'!AF2:AF1048576,"FINAL_AMOUNT_ZOMATO_POS_MISMATCH") | E38: =C38-D38 | F38: =SUMIFS('Zomato POS vs 3PO'!Z2:Z1048576,'Zomato POS vs 3PO'!Z2:Z1048576,"<>",'Zomato POS vs 3PO'!AC2:AC1048576,"UNRECONCILED",'Zomato POS vs 3PO'!AF2:AF1048576,"FINAL_AMOUNT_ZOMATO_POS_MISMATCH") | G38: =COUNTIFS('Zomato 3PO vs POS'!AU2:AU1048576,"UNRECONCILED",'Zomato 3PO vs POS'!AX2:AX1048576,"FINAL_AMOUNT_ZOMATO_POS_MISMATCH") | H38: =SUMIFS('Zomato 3PO vs POS'!E2:E1048576,'Zomato 3PO vs POS'!E2:E1048576,"<>",'Zomato 3PO vs POS'!AU2:AU1048576,"UNRECONCILED",'Zomato 3PO vs POS'!AX2:AX1048576,"FINAL_AMOUNT_ZOMATO_POS_MISMATCH") | I38: =SUMIFS('Zomato 3PO vs POS'!F2:F1048576,'Zomato 3PO vs POS'!F2:F1048576,"<>",'Zomato 3PO vs POS'!AU2:AU1048576,"UNRECONCILED",'Zomato 3PO vs POS'!AX2:AX1048576,"FINAL_AMOUNT_ZOMATO_POS_MISMATCH") | J38: =H38-I38 | K38: =SUMIFS('Zomato 3PO vs POS'!Z2:Z1048576,'Zomato 3PO vs POS'!Z2:Z1048576,"<>",'Zomato 3PO vs POS'!AU2:AU1048576,"UNRECONCILED",'Zomato 3PO vs POS'!AX2:AX1048576,"FINAL_AMOUNT_ZOMATO_POS_MISMATCH")

Sheet Zomato POS vs 3PO
A1: pos_order_id | B1: zomato_order_id | C1: store_name | D1: order_date | E1: pos_net_amount | F1: zomato_net_amount | G1: pos_vs_zomato_net_amount_delta | H1: pos_tax_paid_by_customer | I1: zomato_tax_paid_by_customer | J1: pos_vs_zomato_tax_paid_by_customer_delta | K1: pos_commission_value | L1: zomato_commission_value | M1: pos_vs_zomato_commission_value_delta | N1: pos_pg_applied_on | O1: zomato_pg_applied_on | P1: pos_vs_zomato_pg_applied_on_delta | Q1: pos_pg_charge | R1: zomato_pg_charge | S1: pos_vs_zomato_pg_charge_delta | T1: pos_taxes_zomato_fee | U1: zomato_taxes_zomato_fee | V1: pos_vs_zomato_taxes_zomato_fee_delta | W1: pos_tds_amount | X1: zomato_tds_amount | Y1: pos_vs_zomato_tds_amount_delta | Z1: pos_final_amount | AA1: zomato_final_amount | AB1: pos_vs_zomato_final_amount_delta | AC1: reconciled_status | AD1: reconciled_amount | AE1: unreconciled_amount | AF1: pos_vs_zomato_reason | AG1: order_status_pos

Sheet Zomato 3PO vs POS
A1: zomato_order_id | B1: pos_order_id | C1: order_date | D1: store_name | E1: zomato_net_amount | F1: pos_net_amount | G1: zomato_vs_pos_net_amount_delta | H1: zomato_tax_paid_by_customer | I1: pos_tax_paid_by_customer | J1: zomato_vs_pos_tax_paid_by_customer_delta | K1: zomato_commission_value | L1: pos_commission_value | M1: zomato_vs_pos_commission_value_delta | N1: zomato_pg_applied_on | O1: pos_pg_applied_on | P1: zomato_vs_pos_pg_applied_on_delta | Q1: zomato_pg_charge | R1: pos_pg_charge | S1: zomato_vs_pos_pg_charge_delta | T1: zomato_taxes_zomato_fee | U1: pos_taxes_zomato_fee | V1: zomato_vs_pos_taxes_zomato_fee_delta | W1: zomato_tds_amount | X1: pos_tds_amount | Y1: zomato_vs_pos_tds_amount_delta | Z1: zomato_final_amount | AA1: pos_final_amount | AB1: zomato_vs_pos_final_amount_delta | AC1: calculated_zomato_net_amount | AD1: calculated_zomato_tax_paid_by_customer | AE1: calculated_zomato_commission_value | AF1: calculated_zomato_pg_applied_on | AG1: calculated_zomato_pg_charge | AH1: calculated_zomato_taxes_zomato_fee | AI1: calculated_zomato_tds_amount | AJ1: calculated_zomato_final_amount | AK1: fixed_credit_note_amount | AL1: fixed_pro_discount_passthrough | AM1: fixed_customer_discount | AN1: fixed_rejection_penalty_charge | AO1: fixed_user_credits_charge | AP1: fixed_promo_recovery_adj | AQ1: fixed_icecream_handling | AR1: fixed_icecream_deductions | AS1: fixed_order_support_cost | AT1: fixed_merchant_delivery_charge | AU1: reconciled_status | AV1: reconciled_amount | AW1: unreconciled_amount | AX1: zomato_vs_pos_reason | AY1: order_status_zomato

Sheet Zomato 3PO vs POS Refund
A1: zomato_order_id | B1: pos_order_id | C1: order_date | D1: store_name | E1: zomato_net_amount | F1: pos_net_amount | G1: zomato_vs_pos_net_amount_delta | H1: zomato_tax_paid_by_customer | I1: pos_tax_paid_by_customer | J1: zomato_vs_pos_tax_paid_by_customer_delta | K1: zomato_commission_value | L1: pos_commission_value | M1: zomato_vs_pos_commission_value_delta | N1: zomato_pg_applied_on | O1: pos_pg_applied_on | P1: zomato_vs_pos_pg_applied_on_delta | Q1: zomato_pg_charge | R1: pos_pg_charge | S1: zomato_vs_pos_pg_charge_delta | T1: zomato_taxes_zomato_fee | U1: pos_taxes_zomato_fee | V1: zomato_vs_pos_taxes_zomato_fee_delta | W1: zomato_tds_amount | X1: pos_tds_amount | Y1: zomato_vs_pos_tds_amount_delta | Z1: zomato_final_amount | AA1: pos_final_amount | AB1: zomato_vs_pos_final_amount_delta | AC1: calculated_zomato_net_amount | AD1: calculated_zomato_tax_paid_by_customer | AE1: calculated_zomato_commission_value | AF1: calculated_zomato_pg_applied_on | AG1: calculated_zomato_pg_charge | AH1: calculated_zomato_taxes_zomato_fee | AI1: calculated_zomato_tds_amount | AJ1: calculated_zomato_final_amount | AK1: fixed_credit_note_amount | AL1: fixed_pro_discount_passthrough | AM1: fixed_customer_discount | AN1: fixed_rejection_penalty_charge | AO1: fixed_user_credits_charge | AP1: fixed_promo_recovery_adj | AQ1: fixed_icecream_handling | AR1: fixed_icecream_deductions | AS1: fixed_order_support_cost | AT1: fixed_merchant_delivery_charge | AU1: reconciled_status | AV1: reconciled_amount | AW1: unreconciled_amount | AX1: zomato_vs_pos_reason | AY1: order_status_zomato

Sheet Order not found in POS
A1: zomato_order_id | B1: order_date | C1: store_name | D1: zomato_net_amount | E1: zomato_tax_paid_by_customer | F1: zomato_commission_value | G1: zomato_pg_applied_on | H1: zomato_pg_charge | I1: zomato_taxes_zomato_fee | J1: zomato_tds_amount | K1: zomato_final_amount | L1: calculated_zomato_net_amount | M1: calculated_zomato_tax_paid_by_customer | N1: calculated_zomato_commission_value | O1: calculated_zomato_pg_applied_on | P1: calculated_zomato_pg_charge | Q1: calculated_zomato_taxes_zomato_fee | R1: calculated_zomato_tds_amount | S1: calculated_zomato_final_amount | T1: fixed_credit_note_amount | U1: fixed_pro_discount_passthrough | V1: fixed_customer_discount | W1: fixed_rejection_penalty_charge | X1: fixed_user_credits_charge | Y1: fixed_promo_recovery_adj | Z1: fixed_icecream_handling | AA1: fixed_icecream_deductions | AB1: fixed_order_support_cost | AC1: fixed_merchant_delivery_charge | AD1: reconciled_status | AE1: reconciled_amount | AF1: unreconciled_amount | AG1: zomato_vs_pos_reason | AH1: order_status_zomato

Sheet Order not found in 3PO
A1: pos_order_id | B1: store_name | C1: order_date | D1: pos_net_amount | E1: pos_tax_paid_by_customer | F1: pos_commission_value | G1: pos_pg_applied_on | H1: pos_pg_charge | I1: pos_taxes_zomato_fee | J1: pos_tds_amount | K1: pos_final_amount | L1: reconciled_status | M1: reconciled_amount | N1: unreconciled_amount | O1: pos_vs_zomato_reason | P1: order_status_pos
